Workbook

Sheet Cost Per User
A1: Navia Unit Economics — Cost Per Active User Per Month
A2: Blue cells = assumptions (editable). Black cells = formulas.
A4: Component | B4: Unit cost | C4: Usage / month | D4: Cost / user / month | E4: Source / notes
A5: Claude Opus — input tokens | B5: 15 | C5: 25000 | D5: =B5/1000000*C5 -> 0.375 | E5: Source: Anthropic pricing April 2026
A6: Claude Opus — output tokens | B6: 75 | C6: 6000 | D6: =B6/1000000*C6 -> 0.45 | E6: ~10 interactions, 600 output tokens each
A7: ElevenLabs voice synthesis | B7: 0.3 | C7: 3000 | D7: =B7/1000*C7 -> 0.9 | E7: Source: ElevenLabs Scale plan pricing
A8: Hume emotion detection | B8: 0.005 | C8: 10 | D8: =B8*C8 -> 0.05 | E8: Source: Hume API estimated pricing
A9: Whisper transcription | B9: 0.006 | C9: 8 | D9: =B9*C9 -> 0.048 | E9: Source: OpenAI Whisper API pricing
A10: Cloudflare Workers (edge API) | B10: 0.05 | D10: =B10 -> 0.05 | E10: Flat estimate at scale (bundled pricing)
A11: SQLCipher + infrastructure overhead | B11: 0.12 | D11: =B11 -> 0.12 | E11: DB hosting, backups, monitoring amortized
A12: Stripe payment processing (paid users only) | B12: 0.029 | C12: 0.3 | D12: See Pricing sheet | E12: 2.9% + $0.30 per transaction
A13: Apple App Store commission (paid users) | B13: 0.15 | D13: See Pricing sheet | E13: 15% small business program (< $1M rev)
A15: TOTAL AI + INFRA COST PER ACTIVE USER | D15: =SUM(D5:D11) -> 1.993

Sheet Pricing Scenarios
A1: Pricing Tiers and Margin Analysis
A2: Blue = editable assumptions. Black = formulas.
B4: Free | C4: Companion | D4: Full Presence
A5: Monthly price | B5: 0 | C5: 7.99 | D5: 14.99
A6: Annual price (if offered) | B6: =B5*12 -> 0 | C6: =C5*10 -> 79.9 | D6: =D5*10 -> 149.9 | E6: Annual = 10 months (2 free)
A7: AI + infra cost / user / month | B7: ='Cost Per User'!D15 -> 1.993 | C7: ='Cost Per User'!D15*1.3 -> 2.5909 | D7: ='Cost Per User'!D15*1.8 -> 3.5874 | E7: Companion +30%, Full +80% usage
A8: Apple commission (15%) | B8: =0 -> 0 | C8: =C5*0.15 -> 1.1985 | D8: =D5*0.15 -> 2.2485
A9: Stripe fees (2.9% + $0.30) | B9: =0 -> 0 | C9: =C5*0.029+0.3 -> 0.53171 | D9: =D5*0.029+0.3 -> 0.73471
A10: Total cost per user / month | B10: =B7 -> 1.993 | C10: =C7+C8+C9 -> 4.32111 | D10: =D7+D8+D9 -> 6.57061
A11: Net margin per user / month | B11: =B5-B10 -> -1.993 | C11: =C5-C10 -> 3.66889 | D11: =D5-D10 -> 8.41939
A12: Gross margin % | B12: ="-" -> - | C12: =IF(C5>0,C11/C5,0) -> 0.45918523 | D12: =IF(D5>0,D11/D5,0) -> 0.56166711

Sheet Revenue Projections
A1: Revenue Projections — 24-Month Horizon
A2: Conservative scenario. Blue = editable growth assumptions.
B4: M1 | C4: M2 | D4: M3 | E4: M6 | F4: M9 | G4: M12 | H4: M18 | I4: M24
A5: GROWTH ASSUMPTIONS
A6: Total registered users | B6: 100 | C6: 350 | D6: 800 | E6: 3000 | F6: 6000 | G6: 10000 | H6: 22000 | I6: 40000
A7: Monthly active users (MAU) | B7: 0.7 | C7: 0.65 | D7: 0.6 | E7: 0.55 | F7: 0.5 | G7: 0.48 | H7: 0.45 | I7: 0.42
A8: MAU count | B8: =B6*B7 -> 70 | C8: =C6*C7 -> 227.5 | D8: =D6*D7 -> 480 | E8: =E6*E7 -> 1650 | F8: =F6*F7 -> 3000 | G8: =G6*G7 -> 4800 | H8: =H6*H7 -> 9900 | I8: =I6*I7 -> 16800
A10: CONVERSION RATES
A11: Free to Companion conversion | B11: 0.02 | C11: 0.04 | D11: 0.06 | E11: 0.08 | F11: 0.09 | G11: 0.1 | H11: 0.11 | I11: 0.12
A12: Companion to Full Presence conversion | B12: 0.05 | C12: 0.08 | D12: 0.12 | E12: 0.15 | F12: 0.18 | G12: 0.2 | H12: 0.22 | I12: 0.25
A14: USER MIX
A15: Companion users | B15: =ROUND(B8*B11,0) -> 1 | C15: =ROUND(C8*C11,0) -> 9 | D15: =ROUND(D8*D11,0) -> 29 | E15: =ROUND(E8*E11,0) -> 132 | F15: =ROUND(F8*F11,0) -> 270 | G15: =ROUND(G8*G11,0) -> 480 | H15: =ROUND(H8*H11,0) -> 1089 | I15: =ROUND(I8*I11,0) -> 2016
A16: Full Presence users | B16: =ROUND(B15*B12,0) -> 0 | C16: =ROUND(C15*C12,0) -> 1 | D16: =ROUND(D15*D12,0) -> 3 | E16: =ROUND(E15*E12,0) -> 20 | F16: =ROUND(F15*F12,0) -> 49 | G16: =ROUND(G15*G12,0) -> 96 | H16: =ROUND(H15*H12,0) -> 240 | I16: =ROUND(I15*I12,0) -> 504
A17: Free users | B17: =B8-B15-B16 -> 69 | C17: =C8-C15-C16 -> 217.5 | D17: =D8-D15-D16 -> 448 | E17: =E8-E15-E16 -> 1498 | F17: =F8-F15-F16 -> 2681 | G17: =G8-G15-G16 -> 4224 | H17: =H8-H15-H16 -> 8571 | I17: =I8-I15-I16 -> 14280
A19: MONTHLY REVENUE
A20: Companion revenue | B20: =B15*'Pricing Scenarios'!C5 -> 7.99 | C20: =C15*'Pricing Scenarios'!C5 -> 71.91 | D20: =D15*'Pricing Scenarios'!C5 -> 231.71 | E20: =E15*'Pricing Scenarios'!C5 -> 1054.68 | F20: =F15*'Pricing Scenarios'!C5 -> 2157.3 | G20: =G15*'Pricing Scenarios'!C5 -> 3835.2 | H20: =H15*'Pricing Scenarios'!C5 -> 8701.11 | I20: =I15*'Pricing Scenarios'!C5 -> 16107.84
A21: Full Presence revenue | B21: =B16*'Pricing Scenarios'!D5 -> 0 | C21: =C16*'Pricing Scenarios'!D5 -> 14.99 | D21: =D16*'Pricing Scenarios'!D5 -> 44.97 | E21: =E16*'Pricing Scenarios'!D5 -> 299.8 | F21: =F16*'Pricing Scenarios'!D5 -> 734.51 | G21: =G16*'Pricing Scenarios'!D5 -> 1439.04 | H21: =H16*'Pricing Scenarios'!D5 -> 3597.6 | I21: =I16*'Pricing Scenarios'!D5 -> 7554.96
A22: Total monthly revenue (gross) | B22: =B20+B21 -> 7.99 | C22: =C20+C21 -> 86.9 | D22: =D20+D21 -> 276.68 | E22: =E20+E21 -> 1354.48 | F22: =F20+F21 -> 2891.81 | G22: =G20+G21 -> 5274.24 | H22: =H20+H21 -> 12298.71 | I22: =I20+I21 -> 23662.8
A24: MONTHLY COSTS
A25: AI + infra (all MAU) | B25: =B8*'Cost Per User'!D15 -> 139.51 | C25: =C8*'Cost Per User'!D15 -> 453.4075 | D25: =D8*'Cost Per User'!D15 -> 956.64 | E25: =E8*'Cost Per User'!D15 -> 3288.45 | F25: =F8*'Cost Per User'!D15 -> 5979 | G25: =G8*'Cost Per User'!D15 -> 9566.4 | H25: =H8*'Cost Per User'!D15 -> 19730.7 | I25: =I8*'Cost Per User'!D15 -> 33482.4
A26: Apple commission (15% on paid) | B26: =B22*0.15 -> 1.1985 | C26: =C22*0.15 -> 13.035 | D26: =D22*0.15 -> 41.502 | E26: =E22*0.15 -> 203.172 | F26: =F22*0.15 -> 433.7715 | G26: =G22*0.15 -> 791.136 | H26: =H22*0.15 -> 1844.8065 | I26: =I22*0.15 -> 3549.42
A27: Stripe fees | B27: =(B15+B16)*0.3+B22*0.029 -> 0.53171 | C27: =(C15+C16)*0.3+C22*0.029 -> 5.5201 | D27: =(D15+D16)*0.3+D22*0.029 -> 17.62372 | E27: =(E15+E16)*0.3+E22*0.029 -> 84.87992 | F27: =(F15+F16)*0.3+F22*0.029 -> 179.56249 | G27: =(G15+G16)*0.3+G22*0.029 -> 325.75296 | H27: =(H15+H16)*0.3+H22*0.029 -> 755.36259 | I27: =(I15+I16)*0.3+I22*0.029 -> 1442.2212
A28: Total variable costs | B28: =B25+B26+B27 -> 141.24021 | C28: =C25+C26+C27 -> 471.9626 | D28: =D25+D26+D27 -> 1015.7657 | E28: =E25+E26+E27 -> 3576.5019 | F28: =F25+F26+F27 -> 6592.334 | G28: =G25+G26+G27 -> 10683.289 | H28: =H25+H26+H27 -> 22330.869 | I28: =I25+I26+I27 -> 38474.041
A30: Fixed costs / month (team, tools, hosting base) | B30: 500 | C30: 500 | D30: 500 | E30: 1200 | F30: 2000 | G30: 3500 | H30: 6000 | I30: 10000
A32: NET MONTHLY CONTRIBUTION | B32: =B22-B28-B30 -> -633.25021 | C32: =C22-C28-C30 -> -885.0626 | D32: =D22-D28-D30 -> -1239.0857 | E32: =E22-E28-E30 -> -3422.0219 | F32: =F22-F28-F30 -> -5700.524 | G32: =G22-G28-G30 -> -8909.049 | H32: =H22-H28-H30 -> -16032.159 | I32: =I22-I28-I30 -> -24811.241
A33: Cumulative (running total) | B33: =B32 -> -633.25021 | C33: =B33+C32 -> -1518.3128 | D33: =C33+D32 -> -2757.3985 | E33: =D33+E32 -> -6179.4204 | F33: =E33+F32 -> -11879.944 | G33: =F33+G32 -> -20788.993 | H33: =G33+H32 -> -36821.152 | I33: =H33+I32 -> -61632.394

Sheet Break-Even
A1: Break-Even Analysis
A2: How many paid users to cover costs.
A4: Metric | B4: Companion only | C4: Full Presence only | D4: Blended (70/30)
A5: Price / month | B5: ='Pricing Scenarios'!C5 -> 7.99 | C5: ='Pricing Scenarios'!D5 -> 14.99 | D5: =B5*0.7+C5*0.3 -> 10.09
A6: Net margin / user / month | B6: ='Pricing Scenarios'!C11 -> 3.66889 | C6: ='Pricing Scenarios'!D11 -> 8.41939 | D6: =B6*0.7+C6*0.3 -> 5.09404
A7: Fixed costs / month target | B7: 3500 | C7: 3500 | D7: 3500
A8: Paid users needed to break even | B8: =IF(B6>0,CEILING(B7/B6,1),0) -> 954 | C8: =IF(C6>0,CEILING(C7/C6,1),0) -> 416 | D8: =IF(D6>0,CEILING(D7/D6,1),0) -> 688
A9: At 10% conversion, total MAU needed | B9: =B8/0.1 -> 9540 | C9: =C8/0.1 -> 4160 | D9: =D8/0.1 -> 6880
